ablt_python_api/README.md
ablt_python_api/__init__.py
ablt_python_api/ablt_api_async.py
ablt_python_api/ablt_api_sync.py
ablt_python_api/requirements.txt
ablt_python_api/schemas.py
ablt_python_api/utils/__init__.py
ablt_python_api/utils/exceptions.py
ablt_python_api/utils/logger_config.py
ablt_python_api-0.0.7.dist-info/METADATA
ablt_python_api-0.0.7.dist-info/WHEEL
ablt_python_api-0.0.7.dist-info/licenses/LICENSE
ablt_python_api-0.0.7.dist-info/RECORD
