Metadata-Version: 2.4
Name: ablt_python_api
Version: 0.0.7
Summary: aBLT Python API
Project-URL: Homepage, https://docs.ablt.ai/api_docs/overview
Project-URL: Bug Tracker, https://github.com/ablt-ai/ablt_python_api/issues
Author-email: Iliya Vereshchagin <iliya.vereshchagin@ablt.ai>
Maintainer-email: Iliya Vereshchagin <i.vereshchagin@gmail.com>
License: MIT License
License-File: LICENSE
Keywords: ablt,api,chatbot,gpt
Classifier: Intended Audience :: Developers
Classifier: Intended Audience :: Information Technology
Classifier: License :: OSI Approved :: MIT License
Classifier: Operating System :: OS Independent
Classifier: Programming Language :: Python :: 3.9
Classifier: Programming Language :: Python :: 3.10
Classifier: Programming Language :: Python :: 3.11
Classifier: Programming Language :: Python :: 3.12
Classifier: Programming Language :: Python :: 3.13
Classifier: Topic :: Scientific/Engineering :: Artificial Intelligence
Classifier: Topic :: Scientific/Engineering :: Human Machine Interfaces
Classifier: Topic :: Software Development :: Libraries :: Python Modules
Requires-Python: >=3.9
Requires-Dist: aiohttp
Requires-Dist: asyncio
Requires-Dist: pydantic
Requires-Dist: requests
